MANIFEST.in
README.md
requirements.txt
setup.py
axeman/__init__.py
axeman/certlib.py
axeman/core.py
axeman.egg-info/PKG-INFO
axeman.egg-info/SOURCES.txt
axeman.egg-info/dependency_links.txt
axeman.egg-info/entry_points.txt
axeman.egg-info/requires.txt
axeman.egg-info/top_level.txt