Metadata-Version: 1.1
Name: axeman
Version: 1.14
Summary: Lumberjack is a multi-threaded and concurrent certificate transparency retriever Edit
Home-page: https://github.com/CaliDog/Axeman/
Author: Ryan Sears
Author-email: ryan@calidog.io
License: MIT
Platform: UNKNOWN
Classifier: License :: OSI Approved :: MIT License
Classifier: Topic :: Internet :: WWW/HTTP
Classifier: Topic :: Software Development :: Testing
Classifier: Environment :: Console
Classifier: Operating System :: MacOS :: MacOS X
Classifier: Operating System :: POSIX
Classifier: Programming Language :: Python :: 3
Classifier: Programming Language :: Python :: 3.5
Classifier: Programming Language :: Python :: 3.6
